ludic/__init__.py
ludic/attrs.py
ludic/base.py
ludic/components.py
ludic/elements.py
ludic/format.py
ludic/html.py
ludic/mypy_plugin.py
ludic/py.typed
ludic/types.py
ludic/utils.py
ludic/catalog/__init__.py
ludic/catalog/buttons.py
ludic/catalog/forms.py
ludic/catalog/headers.py
ludic/catalog/icons.py
ludic/catalog/items.py
ludic/catalog/layouts.py
ludic/catalog/lists.py
ludic/catalog/loaders.py
ludic/catalog/messages.py
ludic/catalog/navigation.py
ludic/catalog/pages.py
ludic/catalog/quotes.py
ludic/catalog/tables.py
ludic/catalog/typography.py
ludic/catalog/utils.py
ludic/contrib/__init__.py
ludic/contrib/django/__init__.py
ludic/contrib/django/middlewares.py
ludic/contrib/django/responses.py
ludic/contrib/fastapi/__init__.py
ludic/contrib/fastapi/routing.py
ludic/styles/__init__.py
ludic/styles/collect.py
ludic/styles/highlight.py
ludic/styles/themes.py
ludic/styles/types.py
ludic/styles/utils.py
ludic/web/__init__.py
ludic/web/app.py
ludic/web/datastructures.py
ludic/web/endpoints.py
ludic/web/exceptions.py
ludic/web/parsers.py
ludic/web/requests.py
ludic/web/responses.py
ludic/web/routing.py
ludic-1.0.1.dist-info/METADATA
ludic-1.0.1.dist-info/WHEEL
ludic-1.0.1.dist-info/licenses/LICENCE
ludic-1.0.1.dist-info/RECORD
