Metadata-Version: 2.4
Name: ludic
Version: 1.0.1
Summary: Lightweight framework for building dynamic HTML pages in pure Python with t-strings.
Author-email: Pavel Dedík <dedikx@gmail.com>
Maintainer-email: Pavel Dedík <dedikx@gmail.com>
License-Expression: MIT
License-File: LICENCE
Keywords: async,html,htmx,t-strings,templating,web
Classifier: Development Status :: 5 - Production/Stable
Classifier: Framework :: AnyIO
Classifier: Intended Audience :: Developers
Classifier: License :: OSI Approved :: MIT License
Classifier: Operating System :: OS Independent
Classifier: Programming Language :: Python :: 3 :: Only
Classifier: Programming Language :: Python :: 3.14
Classifier: Programming Language :: Python :: Implementation :: CPython
Classifier: Topic :: Internet :: WWW/HTTP
Requires-Python: >=3.14
Requires-Dist: typing-extensions>=4.9.0
Provides-Extra: dev
Requires-Dist: django; extra == 'dev'
Requires-Dist: django-stubs; extra == 'dev'
Requires-Dist: fastapi; extra == 'dev'
Requires-Dist: mypy; extra == 'dev'
Requires-Dist: pygments; extra == 'dev'
Requires-Dist: python-multipart>=0.0.9; extra == 'dev'
Requires-Dist: starlette; extra == 'dev'
Requires-Dist: typeguard>=4.1.5; extra == 'dev'
Requires-Dist: types-pygments; extra == 'dev'
Requires-Dist: uvicorn; extra == 'dev'
Provides-Extra: django
Requires-Dist: django; extra == 'django'
Provides-Extra: fastapi
Requires-Dist: fastapi; extra == 'fastapi'
Provides-Extra: full
Requires-Dist: pygments; extra == 'full'
Requires-Dist: python-multipart>=0.0.9; extra == 'full'
Requires-Dist: starlette; extra == 'full'
Requires-Dist: typeguard>=4.1.5; extra == 'full'
Requires-Dist: uvicorn; extra == 'full'
Provides-Extra: starlette
Requires-Dist: starlette; extra == 'starlette'
Provides-Extra: test
Requires-Dist: django; extra == 'test'
Requires-Dist: django-stubs; extra == 'test'
Requires-Dist: fastapi; extra == 'test'
Requires-Dist: httpx; extra == 'test'
Requires-Dist: mypy; extra == 'test'
Requires-Dist: pygments; extra == 'test'
Requires-Dist: pytest; extra == 'test'
Requires-Dist: pytest-cov; extra == 'test'
Requires-Dist: python-multipart>=0.0.9; extra == 'test'
Requires-Dist: starlette; extra == 'test'
Requires-Dist: typeguard>=4.1.5; extra == 'test'
Requires-Dist: types-pygments; extra == 'test'
Requires-Dist: uvicorn; extra == 'test'
